vutils/python/__init__.py
vutils/python/__init__.pyi
vutils/python/objects.py
vutils/python/py.typed
vutils/python/version.py
vutils_python-0.2.1.dist-info/LICENSE
vutils_python-0.2.1.dist-info/METADATA
vutils_python-0.2.1.dist-info/WHEEL
vutils_python-0.2.1.dist-info/top_level.txt
vutils_python-0.2.1.dist-info/RECORD
